algopedia/__init__.py
algopedia/ctci/__init__.py
algopedia/ctci/chapter_1.py
algopedia/solver.py
algopedia-0.1.0.dist-info/WHEEL
algopedia-0.1.0.dist-info/METADATA
algopedia-0.1.0.dist-info/RECORD
