Metadata-Version: 2.1
Name: algopedia
Version: 0.1.0
Summary: 
Author: Marcelo Trylesinski
Author-email: marcelotryle@gmail.com
Requires-Python: >=3.8,<4.0
Classifier: Programming Language :: Python :: 3
Classifier: Programming Language :: Python :: 3.8
Provides-Extra: test
Requires-Dist: pydantic (>=1.6.1,<2.0.0)
